mcp_trello/__init__.py
mcp_trello/client.py
mcp_trello/main.py
mbeauv_mcp_trello-0.2.0.dist-info/METADATA
mbeauv_mcp_trello-0.2.0.dist-info/WHEEL
mbeauv_mcp_trello-0.2.0.dist-info/entry_points.txt
mbeauv_mcp_trello-0.2.0.dist-info/licenses/LICENSE
mbeauv_mcp_trello-0.2.0.dist-info/RECORD
