Metadata-Version: 2.4
Name: mbeauv-mcp-trello
Version: 0.2.0
Summary: MCP extension for Trello
Project-URL: Homepage, https://github.com/mbeauv/mcp-trello
Project-URL: Repository, https://github.com/mbeauv/mcp-trello
Project-URL: Issues, https://github.com/mbeauv/mcp-trello/issues
Author-email: Martin Beauvais <mbeauv@gmail.com>
License: MIT License
License-File: LICENSE
Classifier: Development Status :: 3 - Alpha
Classifier: Intended Audience :: Developers
Classifier: License :: OSI Approved :: MIT License
Classifier: Programming Language :: Python :: 3
Classifier: Programming Language :: Python :: 3.11
Classifier: Programming Language :: Python :: 3.12
Requires-Python: >=3.11
Requires-Dist: httpx>=0.24.0
Requires-Dist: mcp-cli>=0.5.2
Requires-Dist: mcp>=1.0.0
Requires-Dist: py-trello>=0.19.0
Requires-Dist: python-dotenv>=1.0.0
Provides-Extra: dev
Requires-Dist: black>=23.0.0; extra == 'dev'
Requires-Dist: flake8>=6.0.0; extra == 'dev'
Requires-Dist: pytest-asyncio>=0.21.0; extra == 'dev'
Requires-Dist: pytest>=7.0.0; extra == 'dev'
